{
  "hosting": {
    "S3AndCloudFront": {
      "service": "S3AndCloudFront",
      "providerPlugin": "awscloudformation"
    }
  },
  "function": {
    "blockdesigna4a7e561CustomMessage": {
      "build": true,
      "providerPlugin": "awscloudformation",
      "service": "Lambda"
    },
    "blockdesign375b8667CustomMessage": {
      "build": true,
      "providerPlugin": "awscloudformation",
      "service": "Lambda"
    }
  },
  "auth": {
    "blockdesign375b8667": {
      "service": "Cognito",
      "providerPlugin": "awscloudformation",
      "dependsOn": [
        {
          "category": "function",
          "resourceName": "blockdesign375b8667CustomMessage",
          "triggerProvider": "Cognito",
          "attributes": [
            "Arn",
            "Name"
          ]
        }
      ],
      "customAuth": false
    }
  },
  "api": {
    "blockdesign": {
      "service": "AppSync",
      "providerPlugin": "awscloudformation",
      "output": {
        "authConfig": {
          "defaultAuthentication": {
            "authenticationType": "AMAZON_COGNITO_USER_POOLS",
            "userPoolConfig": {
              "userPoolId": "authblockdesign375b8667"
            }
          },
          "additionalAuthenticationProviders": []
        }
      }
    }
  }
}